complicator/CoCl4_activity.py
complicator/__init__.py
complicator/autopp93s4.py
complicator/complicator_fit.py
complicator/example_input_file.csv
complicator/wrm_data.csv
complicator/wrm_ligand_abbrv.csv
complicator-0.3.0.dist-info/licenses/LICENSE.txt
complicator-0.3.0.dist-info/METADATA
complicator-0.3.0.dist-info/WHEEL
complicator-0.3.0.dist-info/top_level.txt
complicator-0.3.0.dist-info/RECORD
