Metadata-Version: 2.4
Name: complicator
Version: 0.3.0
Summary: Estimate thermodynamic properties of aqueous metal complexes with monovalent ligands.
Author-email: Grayson Boyer <gmboyer@asu.edu>
License-Expression: MIT
Project-URL: Homepage, https://github.com/gmboyer/complicator
Classifier: Programming Language :: Python :: 3
Classifier: Operating System :: OS Independent
Requires-Python: >=3.10
License-File: LICENSE.txt
Requires-Dist: pandas
Requires-Dist: wormutils
Requires-Dist: chemparse
Dynamic: license-file
